{
  "scraped": "2026-06-20",
  "customers_say": "",
  "aspects": [],
  "reviews": [
    {
      "author": "Ayesha Tabassum",
      "rating": 5.0,
      "title": "",
      "date": "2026-06-14",
      "date_label": "14 June 2026",
      "body": ""
    },
    {
      "author": "Hamaad malik",
      "rating": 5.0,
      "title": "",
      "date": "2026-06-12",
      "date_label": "12 June 2026",
      "body": ""
    },
    {
      "author": "Sita Ram",
      "rating": 5.0,
      "title": "",
      "date": "2026-06-11",
      "date_label": "11 June 2026",
      "body": ""
    },
    {
      "author": "Gandhi Yash",
      "rating": 5.0,
      "title": "",
      "date": "2026-05-23",
      "date_label": "23 May 2026",
      "body": ""
    },
    {
      "author": "MAYANK",
      "rating": 5.0,
      "title": "",
      "date": "2026-05-13",
      "date_label": "13 May 2026",
      "body": ""
    }
  ]
}